cosinor_lite/__init__.py
cosinor_lite/livecell_cosinor_analysis.py
cosinor_lite/livecell_dataset.py
cosinor_lite/omics_dataset.py
cosinor_lite/omics_differential_rhytmicity.py
cosinor_lite-0.1.5.dist-info/WHEEL
cosinor_lite-0.1.5.dist-info/METADATA
cosinor_lite-0.1.5.dist-info/RECORD
