Metadata-Version: 2.3
Name: cosinor-lite
Version: 0.1.5
Summary: A simplified package for cosinor analysis of circadian bioluminescent, fluorescent and omics datasets
Author: Nick Phillips
Author-email: Nick Phillips <nicholas.phillips@hug.ch>
License: Apache-2.0
Classifier: Programming Language :: Python :: 3
Requires-Dist: numpy
Requires-Dist: matplotlib
Requires-Dist: pandas
Requires-Dist: pandas-stubs
Requires-Dist: jupyterlab
Requires-Dist: scipy
Requires-Dist: statsmodels
Requires-Dist: astropy
Requires-Dist: pingouin
Requires-Dist: pydantic>=2.11.9
Requires-Dist: tqdm>=4.67.1
Requires-Dist: openpyxl>=3.1.5
Requires-Dist: gradio>=5.50.0
Requires-Python: >=3.11
